extended_mypy_django_plugin/__init__.py
extended_mypy_django_plugin/annotations.py
extended_mypy_django_plugin/main.py
extended_mypy_django_plugin/plugin.py
extended_mypy_django_plugin/py.typed
extended_mypy_django_plugin/version.py
extended_mypy_django_plugin/_plugin/__init__.py
extended_mypy_django_plugin/_plugin/analyze.py
extended_mypy_django_plugin/_plugin/annotation_resolver.py
extended_mypy_django_plugin/_plugin/config.py
extended_mypy_django_plugin/_plugin/debug.py
extended_mypy_django_plugin/_plugin/entry.py
extended_mypy_django_plugin/_plugin/hook.py
extended_mypy_django_plugin/_plugin/plugin.py
extended_mypy_django_plugin/_plugin/protocols.py
extended_mypy_django_plugin/_plugin/type_checker.py
extended_mypy_django_plugin/_plugin/virtual_dependencies.py
extended_mypy_django_plugin/django_analysis/__init__.py
extended_mypy_django_plugin/django_analysis/fields.py
extended_mypy_django_plugin/django_analysis/hasher.py
extended_mypy_django_plugin/django_analysis/models.py
extended_mypy_django_plugin/django_analysis/modules.py
extended_mypy_django_plugin/django_analysis/project.py
extended_mypy_django_plugin/django_analysis/protocols.py
extended_mypy_django_plugin/django_analysis/discovery/__init__.py
extended_mypy_django_plugin/django_analysis/discovery/concrete_models.py
extended_mypy_django_plugin/django_analysis/discovery/container.py
extended_mypy_django_plugin/django_analysis/discovery/import_path.py
extended_mypy_django_plugin/django_analysis/discovery/known_models.py
extended_mypy_django_plugin/django_analysis/discovery/settings_types.py
extended_mypy_django_plugin/django_analysis/virtual_dependencies/__init__.py
extended_mypy_django_plugin/django_analysis/virtual_dependencies/dependency.py
extended_mypy_django_plugin/django_analysis/virtual_dependencies/folder.py
extended_mypy_django_plugin/django_analysis/virtual_dependencies/handler.py
extended_mypy_django_plugin/django_analysis/virtual_dependencies/namer.py
extended_mypy_django_plugin-0.8.1.dist-info/METADATA
extended_mypy_django_plugin-0.8.1.dist-info/WHEEL
extended_mypy_django_plugin-0.8.1.dist-info/licenses/LICENSE
extended_mypy_django_plugin-0.8.1.dist-info/RECORD
