Metadata-Version: 2.4
Name: extended-mypy-django-plugin
Version: 0.8.1
Summary: Trying to make mypy understand .objects on abstract django models
Author-email: Stephen Moore <stephen@delfick.com>
License: MIT
License-File: LICENSE
Requires-Python: >=3.10
